README.md
setup.py
Mess_Server_al.egg-info/PKG-INFO
Mess_Server_al.egg-info/SOURCES.txt
Mess_Server_al.egg-info/dependency_links.txt
Mess_Server_al.egg-info/requires.txt
Mess_Server_al.egg-info/top_level.txt
server/__init__.py
server/server.py
server/config/__init__.py
server/config/settings.py
server/config/utils.py
server/logs/__init__.py
server/logs/server_log_config.py
server/serverapp/__init__.py
server/serverapp/config_window.py
server/serverapp/database_server.py
server/serverapp/decorators.py
server/serverapp/descrptrs_server.py
server/serverapp/errors.py
server/serverapp/metaclss_server.py
server/serverapp/server_gui.py
server/unittests/__init__.py
server/unittests/test_utils.py