Metadata-Version: 1.0
Name: Mess-Server-al
Version: 0.0.2
Summary: Messenger_Server
Home-page: UNKNOWN
Author: Alena Vetrova
Author-email: geekbr.alena.vetr@gmail.com
License: UNKNOWN
Platform: UNKNOWN
